drune/__init__.py
drune/cli/__init__.py
drune/cli/main.py
drune/core/__init__.py
drune/core/engine.py
drune/core/main.py
drune/core/metadata.py
drune/core/pipeline.py
drune/core/quality.py
drune/core/step.py
drune/engines/__init__.py
drune/engines/duckdb/__init__.py
drune/engines/pandas/__init__.py
drune/engines/pandas/pandas_engine.py
drune/engines/pandas/steps/__init__.py
drune/engines/pandas/steps/reader.py
drune/engines/pandas/steps/transformer.py
drune/engines/pandas/steps/validator.py
drune/engines/pandas/steps/writer.py
drune/engines/polars/__init__.py
drune/engines/postgres/__init__.py
drune/engines/spark/__init__.py
drune/engines/spark/spark_engine.py
drune/engines/spark/quality/__init__.py
drune/engines/spark/quality/rules.py
drune/engines/spark/steps/__init__.py
drune/engines/spark/steps/reader.py
drune/engines/spark/steps/tester.py
drune/engines/spark/steps/transformer.py
drune/engines/spark/steps/validator.py
drune/engines/spark/steps/writer.py
drune/metadata/__init__.py
drune/metadata/hive/__init__.py
drune/metadata/local/__init__.py
drune/metadata/openmetadata/__init__.py
drune/metadata/unity_catalog/__init__.py
drune/models/__init__.py
drune/models/pipeline_model.py
drune/models/project_model.py
drune/utils/__init__.py
drune/utils/exceptions.py
drune/utils/logger.py
drune-0.1.0.dist-info/METADATA
drune-0.1.0.dist-info/WHEEL
drune-0.1.0.dist-info/entry_points.txt
drune-0.1.0.dist-info/top_level.txt
drune-0.1.0.dist-info/RECORD
