Metadata-Version: 2.4
Name: drune
Version: 0.1.0
Summary: A declarative framework for data pipelines.
Author: Felipe Sampaio
Classifier: Programming Language :: Python :: 3
Classifier: License :: OSI Approved :: MIT License
Classifier: Operating System :: OS Independent
Classifier: Development Status :: 4 - Beta
Classifier: Intended Audience :: Developers
Classifier: Topic :: Software Development :: Libraries
Requires-Python: >=3.8
Requires-Dist: pyyaml
Requires-Dist: pydantic
Requires-Dist: pydantic-yaml
Requires-Dist: click
Provides-Extra: dev
Requires-Dist: pytest; extra == "dev"
Requires-Dist: pytest-cov; extra == "dev"
Requires-Dist: black; extra == "dev"
Requires-Dist: isort; extra == "dev"
Requires-Dist: flake8; extra == "dev"
Requires-Dist: mypy; extra == "dev"
Provides-Extra: spark
Requires-Dist: pyspark>=3.0.0; extra == "spark"
Provides-Extra: duckdb
Requires-Dist: duckdb>=0.5.0; extra == "duckdb"
Provides-Extra: pandas
Requires-Dist: pandas>=1.0.0; extra == "pandas"
Provides-Extra: polars
Requires-Dist: polars>=0.10.0; extra == "polars"
Provides-Extra: all
Requires-Dist: drune[spark]; extra == "all"
Requires-Dist: drune[duckdb]; extra == "all"
Requires-Dist: drune[pandas]; extra == "all"
Requires-Dist: drune[polars]; extra == "all"
